morelogin_mcp/__init__.py
morelogin_mcp/mcp_handler.py
morelogin_mcp/morelogin_client.py
morelogin_mcp-0.1.1.dist-info/LICENSE
morelogin_mcp-0.1.1.dist-info/METADATA
morelogin_mcp-0.1.1.dist-info/WHEEL
morelogin_mcp-0.1.1.dist-info/top_level.txt
morelogin_mcp-0.1.1.dist-info/RECORD
